rtopy/__init__.py
rtopy/bridge.py
rtopy/cli.py
rtopy/exceptions.py
rtopy/rtopy.py
rtopy/utils.py
rtopy-0.2.0.dist-info/licenses/LICENSE
tests/__init__.py
tests/test_rtopy.py
rtopy-0.2.0.dist-info/METADATA
rtopy-0.2.0.dist-info/WHEEL
rtopy-0.2.0.dist-info/top_level.txt
rtopy-0.2.0.dist-info/RECORD
