Metadata-Version: 2.4
Name: rtopy
Version: 0.2.0
Summary: Lightweight bridge for calling R functions from Python
Home-page: https://github.com/thierrymoudiki/rtopy
Author: T. Moudiki (forked and improved)
Author-email: "T. Moudiki" <thierry.moudiki@gmail.com>
License-Expression: BSD-3-Clause
Project-URL: Homepage, https://github.com/Techtonique/rtopy
Project-URL: Repository, https://github.com/Techtonique/rtopy
Project-URL: Issues, https://github.com/Techtonique/rtopy/issues
Keywords: r,python,bridge,statistics,data-science
Classifier: Development Status :: 4 - Beta
Classifier: Intended Audience :: Developers
Classifier: Intended Audience :: Science/Research
Classifier: Programming Language :: Python :: 3
Classifier: Programming Language :: Python :: 3.7
Classifier: Programming Language :: Python :: 3.8
Classifier: Programming Language :: Python :: 3.9
Classifier: Programming Language :: Python :: 3.10
Classifier: Programming Language :: Python :: 3.11
Requires-Python: >=3.7
License-File: LICENSE
Provides-Extra: full
Requires-Dist: numpy>=1.19.0; extra == "full"
Requires-Dist: pandas>=1.1.0; extra == "full"
Provides-Extra: dev
Requires-Dist: pytest>=6.0; extra == "dev"
Requires-Dist: pytest-cov>=2.10; extra == "dev"
Requires-Dist: black>=21.0; extra == "dev"
Requires-Dist: flake8>=3.8; extra == "dev"
Dynamic: author
Dynamic: home-page
Dynamic: license-file
Dynamic: requires-python
